UEQanalyzer/__init__.py
UEQanalyzer/_version.py
UEQanalyzer/analysis.py
UEQanalyzer/data_loader.py
UEQanalyzer/visualization.py
tests/__init__.py
tests/test_analysis.py
tests/test_data_loader.py
ueqanalyzer-0.1.1.data/scripts/cli.py
ueqanalyzer-0.1.1.dist-info/licenses/LICENSE
ueqanalyzer-0.1.1.dist-info/METADATA
ueqanalyzer-0.1.1.dist-info/WHEEL
ueqanalyzer-0.1.1.dist-info/entry_points.txt
ueqanalyzer-0.1.1.dist-info/top_level.txt
ueqanalyzer-0.1.1.dist-info/RECORD
