Metadata-Version: 2.4
Name: UEQanalyzer
Version: 0.1.1
Summary: A Python package for analyzing and visualizing User Experience Questionnaire (UEQ) data.
Home-page: https://github.com/Pranj99/UEQAnalysis
Author: Pranjali Barve
License: MIT
Classifier: Development Status :: 3 - Alpha
Classifier: Programming Language :: Python :: 3
Classifier: License :: OSI Approved :: MIT License
Classifier: Operating System :: OS Independent
Requires-Python: >=3.6
License-File: LICENSE
Requires-Dist: pandas
Requires-Dist: matplotlib
Requires-Dist: openpyxl
Dynamic: author
Dynamic: classifier
Dynamic: description
Dynamic: description-content-type
Dynamic: home-page
Dynamic: license
Dynamic: license-file
Dynamic: requires-dist
Dynamic: requires-python
Dynamic: summary
